README.txt
setup.py
openmetadata/__init__.py
openmetadata/__main__.py
openmetadata/api.py
openmetadata/cli.py
openmetadata/error.py
openmetadata/lib.py
openmetadata/path.py
openmetadata/test.py
openmetadata/upgrade.py
openmetadata/util.py
openmetadata/version.py
openmetadata.egg-info/PKG-INFO
openmetadata.egg-info/SOURCES.txt
openmetadata.egg-info/dependency_links.txt
openmetadata.egg-info/entry_points.txt
openmetadata.egg-info/not-zip-safe
openmetadata.egg-info/top_level.txt
openmetadata/examples/__init__.py
openmetadata/examples/basic.py
openmetadata/examples/convenience.py
openmetadata/examples/diskspace.py
openmetadata/examples/inheritance.py
openmetadata/examples/performance.py
openmetadata/tests/__init__.py
openmetadata/tests/test_cli.py
openmetadata/tests/test_entry.py
openmetadata/tests/test_entry_read.py
openmetadata/tests/test_entry_write.py
openmetadata/tests/test_history.py
openmetadata/tests/test_inherit.py
openmetadata/tests/test_read.py
openmetadata/tests/test_types.py
openmetadata/tests/test_upgrade.py
openmetadata/tests/test_write.py
openmetadata/vendor/__init__.py
openmetadata/vendor/click/__init__.py
openmetadata/vendor/click/_bashcomplete.py
openmetadata/vendor/click/_compat.py
openmetadata/vendor/click/_termui_impl.py
openmetadata/vendor/click/_textwrap.py
openmetadata/vendor/click/core.py
openmetadata/vendor/click/decorators.py
openmetadata/vendor/click/exceptions.py
openmetadata/vendor/click/formatting.py
openmetadata/vendor/click/parser.py
openmetadata/vendor/click/termui.py
openmetadata/vendor/click/testing.py
openmetadata/vendor/click/types.py
openmetadata/vendor/click/utils.py
openmetadata/vendor/yaml/__init__.py
openmetadata/vendor/yaml/_cyaml.py
openmetadata/vendor/yaml/composer.py
openmetadata/vendor/yaml/constructor.py
openmetadata/vendor/yaml/dumper.py
openmetadata/vendor/yaml/emitter.py
openmetadata/vendor/yaml/error.py
openmetadata/vendor/yaml/events.py
openmetadata/vendor/yaml/loader.py
openmetadata/vendor/yaml/nodes.py
openmetadata/vendor/yaml/parser.py
openmetadata/vendor/yaml/reader.py
openmetadata/vendor/yaml/representer.py
openmetadata/vendor/yaml/resolver.py
openmetadata/vendor/yaml/scanner.py
openmetadata/vendor/yaml/serializer.py
