Metadata-Version: 1.1
Name: openmetadata
Version: 0.5.6
Summary: Open Metadata
Home-page: https://github.com/abstractfactory/openmetadata
Author: Marcus Ottosson
Author-email: marcus@abstractfactory.com
License: LICENSE.txt
Platform: UNKNOWN
Classifier: Development Status :: 3 - Alpha
Classifier: Intended Audience :: Developers
Classifier: License :: OSI Approved :: GNU Lesser General Public License v3 (LGPLv3)
Classifier: Programming Language :: Python
Classifier: Programming Language :: Python :: 2
Classifier: Programming Language :: Python :: 2.6
Classifier: Programming Language :: Python :: 2.7
Classifier: Topic :: Software Development :: Libraries :: Python Modules
Classifier: Topic :: Utilities
